micpy/__init__.py
micpy/bin.py
micpy/geo.py
micpy/matplotlib.py
micpy/tab.py
micpy/utils.py
micpy/version.py
micress_micpy-0.2.12.dist-info/LICENSE
micress_micpy-0.2.12.dist-info/METADATA
micress_micpy-0.2.12.dist-info/WHEEL
micress_micpy-0.2.12.dist-info/top_level.txt
micress_micpy-0.2.12.dist-info/RECORD
