Metadata-Version: 2.1
Name: micress-micpy
Version: 0.2.12
Summary: MicPy is a Python package to facilitate MICRESS workflows.
Author: Lukas Koschmieder
Author-email: l.koschmieder@access-technology.de
License: BSD-3-Clause
Keywords: MICRESS
Classifier: Development Status :: 3 - Alpha
Classifier: Intended Audience :: Science/Research
Classifier: Natural Language :: English
Classifier: Operating System :: OS Independent
Classifier: Programming Language :: Python :: 3.9
Requires-Python: >=3.9
License-File: LICENSE
Requires-Dist: matplotlib
Requires-Dist: pandas
